cs.linguacopier-1.3-py3.11-nspkg.pth
cs/linguacopier/__init__.py
cs/linguacopier/configure.zcml
cs/linguacopier/interfaces.py
cs/linguacopier/setuphandlers.py
cs/linguacopier/testing.py
cs/linguacopier/browser/__init__.py
cs/linguacopier/browser/configure.zcml
cs/linguacopier/browser/copier.py
cs/linguacopier/locales/cs.linguacopier.pot
cs/linguacopier/locales/update.sh
cs/linguacopier/profiles/default/actions.xml
cs/linguacopier/profiles/default/browserlayer.xml
cs/linguacopier/profiles/default/metadata.xml
cs/linguacopier/profiles/default/registry.xml
cs/linguacopier/profiles/uninstall/actions.xml
cs/linguacopier/profiles/uninstall/browserlayer.xml
cs/linguacopier/tests/__init__.py
cs/linguacopier/tests/test_setup.py
cs.linguacopier-1.3.dist-info/METADATA
cs.linguacopier-1.3.dist-info/WHEEL
cs.linguacopier-1.3.dist-info/entry_points.txt
cs.linguacopier-1.3.dist-info/namespace_packages.txt
cs.linguacopier-1.3.dist-info/top_level.txt
cs.linguacopier-1.3.dist-info/RECORD
