Metadata-Version: 2.2
Name: cs.linguacopier
Version: 1.3
Summary: Content-copier useful to copy basic content from one language-tree to another to start working with the whole content-tree
Home-page: https://pypi.python.org/pypi/cs.linguacopier
Author: Mikel Larreategi
Author-email: mlarreategi@codesyntax.com
License: GPL version 2
Keywords: Python Plone
Classifier: Environment :: Web Environment
Classifier: Framework :: Plone
Classifier: Framework :: Plone :: 6.0
Classifier: Programming Language :: Python
Classifier: Programming Language :: Python :: 3
Classifier: Operating System :: OS Independent
Classifier: License :: OSI Approved :: GNU General Public License v2 (GPLv2)
Requires-Dist: plone.api
Requires-Dist: Products.GenericSetup>=1.8.2
Requires-Dist: setuptools
Requires-Dist: plone.app.multilingual
Provides-Extra: test
Requires-Dist: plone.app.testing; extra == "test"
Requires-Dist: plone.testing; extra == "test"
Requires-Dist: plone.app.contenttypes; extra == "test"
Requires-Dist: plone.app.robotframework[debug]; extra == "test"
Dynamic: author
Dynamic: author-email
Dynamic: classifier
Dynamic: description
Dynamic: home-page
Dynamic: keywords
Dynamic: license
Dynamic: provides-extra
Dynamic: requires-dist
Dynamic: summary
